{
  "project_info": {
    "project_number": "63376744840",
    "project_id": "ai-pencil",
    "storage_bucket": "ai-pencil.appspot.com"
  },
  "client": [
    {
      "client_info": {
        "mobilesdk_app_id": "1:63376744840:android:2d74a7979809becf715a3d",
        "android_client_info": {
          "package_name": "io.aipencil"
        }
      },
      "oauth_client": [
        {
          "client_id": "63376744840-lslsa2tm3deeeo9smi9mt49adpbrttmg.apps.googleusercontent.com",
          "client_type": 3
        }
      ],
      "api_key": [
        {
          "current_key": "AIzaSyC7yNHW9h9iifjW2dOidBjHiH_NLiVVbsY"
        }
      ],
      "services": {
        "appinvite_service": {
          "other_platform_oauth_client": [
            {
              "client_id": "63376744840-lslsa2tm3deeeo9smi9mt49adpbrttmg.apps.googleusercontent.com",
              "client_type": 3
            }
          ]
        }
      }
    }
  ],
  "configuration_version": "1"
}